<beans xmlns="http://www.springframework.org/schema/beans"
       xmlns:xsi="http://www.w3.org/2001/XMLSchema-instance"
       xmlns:context="http://www.springframework.org/schema/context"
       xmlns:mvc="http://www.springframework.org/schema/mvc"
       xsi:schemaLocation="http://www.springframework.org/schema/beans
        http://www.springframework.org/schema/beans/spring-beans.xsd
        http://www.springframework.org/schema/context http://www.springframework.org/schema/context/spring-context.xsd
       http://www.springframework.org/schema/mvc http://www.springframework.org/schema/mvc/spring-mvc-4.0.xsd">

    <context:component-scan base-package="com.project.forupets"/>

    <bean class="org.springframework.web.servlet.view.InternalResourceViewResolver">
        <property name="prefix" value="/WEB-INF/views/"/>
        <property name="suffix" value=".jsp"/>
    </bean>

    <!-- <bean class="fpt.edu.vn.forum.common.CustomPropertyPlaceholderConfigurer" /> -->
    <bean class="org.springframework.beans.factory.config.PropertyPlaceholderConfigurer">
        <property name="location" value="classpath:database/database.properties"></property>
    </bean>

    <mvc:annotation-driven />

    <!-- Enables the Spring MVC @Controller programming model -->
    <!-- <context:annotation-config/> -->

    <mvc:resources mapping="/resources/**" location="/resources/" />

    <bean id="messageSource"
          class="org.springframework.context.support.ResourceBundleMessageSource">
        <property name="basename" value="locale/message" />
        <property name="defaultEncoding" value="UTF-8" />
    </bean>

    <!-- **************************************************************** -->
    <!-- THYMELEAF-SPECIFIC ARTIFACTS -->
    <!-- TemplateResolver <- TemplateEngine <- ViewResolver -->
    <!-- **************************************************************** -->


    <bean id="templateResolver"
          class="org.thymeleaf.templateresolver.ServletContextTemplateResolver">
        <property name="prefix" value="/WEB-INF/views/" />
        <property name="suffix" value=".html" />
        <property name="templateMode" value="HTML5" />
        <property name="characterEncoding" value="UTF-8"></property>
        <property name="cacheable" value="false" />
    </bean>

    <bean id="templateEngine" class="org.thymeleaf.spring3.SpringTemplateEngine">
        <property name="templateResolver" ref="templateResolver" />
    </bean>

    <bean class="org.thymeleaf.spring3.view.ThymeleafViewResolver">
        <property name="templateEngine" ref="templateEngine" />
        <property name="characterEncoding" value="UTF-8" />
    </bean>

    <!-- DATABASE -->

    <!-- Transaction manager -->
    <bean id="transactionManager"
          class="org.springframework.orm.hibernate4.HibernateTransactionManager">
        <property name="sessionFactory" ref="sessionFactory" />
    </bean>

    <!-- Hibernate session factory -->
    <bean id="sessionFactory"
          class="org.springframework.orm.hibernate4.LocalSessionFactoryBean">
        <property name="dataSource">
            <ref bean="projectDataSource" />
        </property>
        <property name="packagesToScan">
            <list>
                <value>com.project.forupets</value>
            </list>
        </property>
        <property name="hibernateProperties">
            <props>
                <prop key="hibernate.dialect">org.hibernate.dialect.MySQLInnoDBDialect</prop>
                <prop key="hibernate.hbm2ddl.auto">validate</prop>
                <prop key="hibernate.show_sql">true</prop>
                <prop key="hibernate.format_sql">true</prop>
                <prop key="cache.provider_class">org.hibernate.cache.NoCacheProvider</prop>
                <prop key="hibernate.cache.use_second_level_cache">false</prop>
                <prop key="hibernate.current_session_context_class">
                    org.springframework.orm.hibernate4.SpringSessionContext
                </prop>
                <prop key="hibernate.connection.url">jdbc:mysql://localhost:3306/4upets</prop>
                <prop key="hibernate.connection.driver_class">com.mysql.jdbc.Driver</prop>
            </props>
        </property>
    </bean>
    <bean id="projectDataSource" class="org.apache.commons.dbcp.BasicDataSource"
          destroy-method="close">
        <property name="driverClassName" value="${data.driverClassName}" />
        <property name="url" value="${data.url}" />
        <property name="username" value="${data.username}" />
        <property name="password" value="${data.password}" />
        <property name="poolPreparedStatements">
            <value>true</value>
        </property>
        <property name="maxActive">
            <value>10</value>
        </property>
        <property name="maxIdle">
            <value>10</value>
        </property>
        <property name="validationQuery">
            <value>select 1 as dbcp_connection_test</value>
        </property>
    </bean>



</beans>